processor/DldFlashDataframeCreator.py
processor/DldFlashDataframeCreatorExpress.py
processor/DldProcessor.py
processor/LabDataframeCreator.py
processor/__init__.py
processor/channels.json
processor/channels_lab.json
processor/pah.py
processor/cscripts/DldFlashProcessorNotCy.py
processor/cscripts/__init__.py
processor/legacy/__init__.py
processor/legacy/bin/__init__.py
processor/legacy/bin/binningTest.py
processor/legacy/bin/dataframe_creator.py
processor/legacy/processor/DldFlashDataframeCreator.py
processor/legacy/processor/__init__.py
processor/legacy/processor/pah.py
processor/utilities/__init__.py
processor/utilities/calibration.py
processor/utilities/dfops.py
processor/utilities/diagnostics.py
processor/utilities/io.py
processor/utilities/misc.py
processor/utilities/vis.py
processor/utilities/MaskingTool/__init__.py
processor/utilities/MaskingTool/makemask.py
processor/utilities/XPSdoniachs/__init__.py
processor/utilities/XPSdoniachs/setup.py
hextof_processor-1.1.0.dist-info/LICENCE
hextof_processor-1.1.0.dist-info/METADATA
hextof_processor-1.1.0.dist-info/WHEEL
hextof_processor-1.1.0.dist-info/top_level.txt
hextof_processor-1.1.0.dist-info/RECORD
