Metadata-Version: 2.1
Name: hextof-processor
Version: 1.1.0
Summary: Hextof Offline Analyzer
Home-page: https://github.com/momentoscope/hextof-processor
Author: Yves Acremann, Steinn Ymir Agustsson, Davide Curcio, Maciej Dendzik, Michael Heber, Muhammad Zain Sohail, Rui Patrick Xian
Author-email: zainsohail04@gmail.com
License: UNKNOWN
Project-URL: Bug Tracker, https://github.com/momentoscope/hextof-processor/issues
Platform: UNKNOWN
Classifier: Programming Language :: Python :: 3
Classifier: Programming Language :: Python :: 3.8
Classifier: Programming Language :: Python :: 3.9
Classifier: License :: OSI Approved :: GNU General Public License v3 (GPLv3)
Classifier: Operating System :: OS Independent
Requires-Python: >=3.8
License-File: LICENCE
Requires-Dist: numpy (>=1.14.2)
Requires-Dist: matplotlib (>=2.1.0)
Requires-Dist: pandas (>=0.20.3)
Requires-Dist: h5py (>=2.7.1)
Requires-Dist: dask (>=0.17.3)
Requires-Dist: xarray (>=0.9.6)
Requires-Dist: tqdm (>=4.31.1)
Requires-Dist: scipy (>=1.2.1)
Requires-Dist: fastparquet (>=0.2.1)
Requires-Dist: pyarrow (>=0.12.1)
Requires-Dist: psutil
Requires-Dist: tifffile
